clog/__init__.py
clog/clog.py
CLogs_Ulif-1.0.0.dist-info/LICENSE
CLogs_Ulif-1.0.0.dist-info/METADATA
CLogs_Ulif-1.0.0.dist-info/WHEEL
CLogs_Ulif-1.0.0.dist-info/top_level.txt
CLogs_Ulif-1.0.0.dist-info/RECORD
