Metadata-Version: 2.1
Name: CLogs-Ulif
Version: 1.0.0
Summary: A library for creating changelog programmatically with ease.
Author-email: UlifSystems <ulifsystems@gmail.com>
Project-URL: Homepage, https://github.com/ulifprojects/clogs
Project-URL: Bug Tracker, https://github.com/ulifprojects/clogs/issues
Classifier: Programming Language :: Python :: 3
Classifier: License :: OSI Approved :: MIT License
Classifier: Operating System :: OS Independent
Requires-Python: >=3.10
License-File: LICENSE
